mask_gpu/__init__.py
mask_gpu/command_line.py
mask_gpu-0.1.0.dist-info/LICENCE
mask_gpu-0.1.0.dist-info/METADATA
mask_gpu-0.1.0.dist-info/WHEEL
mask_gpu-0.1.0.dist-info/entry_points.txt
mask_gpu-0.1.0.dist-info/top_level.txt
mask_gpu-0.1.0.dist-info/RECORD
