Metadata-Version: 2.1
Name: mask-gpu
Version: 0.1.0
Summary: A simple tool to show specified number of GPUs with desired memory to Tensorflow
Home-page: https://github.com/saravanabalagi/mask-gpu
Author: Saravanabalagi Ramachandran
Author-email: saravanabalagi@hotmail.com
License: MIT
Platform: UNKNOWN
Classifier: Development Status :: 3 - Alpha
Classifier: Topic :: Software Development :: Libraries
Classifier: License :: OSI Approved :: MIT License
Classifier: Programming Language :: Python :: 3
Classifier: Programming Language :: Python :: 3.6
Classifier: Programming Language :: Python :: 3.7
